pyinotifyd/__init__.py
pyinotifyd/_install.py
pyinotifyd/scheduler.py
pyinotifyd/misc/config.py.default
pyinotifyd/misc/openrc/pyinotifyd.confd
pyinotifyd/misc/openrc/pyinotifyd.initd
pyinotifyd/misc/systemd/pyinotifyd.service
pyinotifyd-0.0.9.dist-info/LICENSE
pyinotifyd-0.0.9.dist-info/METADATA
pyinotifyd-0.0.9.dist-info/WHEEL
pyinotifyd-0.0.9.dist-info/entry_points.txt
pyinotifyd-0.0.9.dist-info/top_level.txt
pyinotifyd-0.0.9.dist-info/RECORD
