Metadata-Version: 2.1
Name: pyinotifyd
Version: 0.0.9
Summary: Monitoring filesystems events with inotify on Linux and execute tasks.
Home-page: https://github.com/spacefreak86/pyinotifyd
Author: Thomas Oettli
Author-email: spacefreak@noop.ch
License: GPL 3
Keywords: inotify daemon
Classifier: Development Status :: 5 - Production/Stable
Classifier: License :: OSI Approved :: GNU General Public License v3 or later (GPLv3+)
Classifier: Operating System :: OS Independent
Classifier: Programming Language :: Python
Classifier: Programming Language :: Python :: 3
Classifier: Topic :: Utilities
Requires-Python: >=3.7
License-File: LICENSE
Requires-Dist: pyinotify
